{
   "abstract" : "Basic implementation of the XDG base directory specification",
   "author" : [
      "Kiyoshi Aman <kiyoshi.aman@gmail.com>"
   ],
   "dynamic_config" : 1,
   "generated_by" : "Module::Build version 0.38, CPAN::Meta::Converter version 2.110440",
   "license" : [
      "perl_5"
   ],
   "meta-spec" : {
      "url" : "http://search.cpan.org/perldoc?CPAN::Meta::Spec",
      "version" : "2"
   },
   "name" : "File-XDG",
   "prereqs" : {
      "runtime" : {
         "requires" : {
            "File::HomeDir" : 0,
            "Path::Class" : 0,
            "perl" : "v5.10.0"
         }
      }
   },
   "provides" : {
      "File::XDG" : {
         "file" : "lib/File/XDG.pm",
         "version" : "0.03"
      }
   },
   "release_status" : "stable",
   "resources" : {
      "license" : [
         "http://dev.perl.org/licenses/"
      ]
   },
   "version" : "0.03"
}
